{
    "backdrop_path": "/7VEUOEfRzzrQfWddlIyLUKvh6Nf.jpg",
    "id": 447277,
    "original_title": "The Little Mermaid",
    "overview": "The youngest of King Triton\u2019s daughters, and the most defiant, Ariel longs to find out more about the world beyond the sea, and while visiting the surface, falls for the dashing Prince Eric. With mermaids forbidden to interact with humans, Ariel makes a deal with the evil sea witch, Ursula, which gives her a chance to experience life on land, but ultimately places her life \u2013 and her father\u2019s crown \u2013 in jeopardy.",
    "poster_path": "/ym1dxyOk4jFcSl4Q2zmRrA5BEEN.jpg",
    "media_type": "movie",
    "adult": false,
    "title": "The Little Mermaid",
    "original_language": "en",
    "genre_ids": [
        12,
        10751,
        14,
        10749
    ],
    "popularity": 131.872,
    "release_date": "2023-05-18",
    "video": false,
    "vote_average": 6.385,
    "vote_count": 2723
}